minimalagent/__init__.py
minimalagent/agent.py
minimalagent/models.py
minimalagent/py.typed
minimalagent/session.py
minimalagent/tool.py
minimalagent/utils/__init__.py
minimalagent/utils/docstring.py
minimalagent/utils/logging.py
minimalagent/utils/reasoning_display.py
minimalagent/utils/tools.py
minimalagent-0.2.7.dist-info/LICENSE
minimalagent-0.2.7.dist-info/METADATA
minimalagent-0.2.7.dist-info/WHEEL
minimalagent-0.2.7.dist-info/top_level.txt
minimalagent-0.2.7.dist-info/RECORD
