Metadata-Version: 2.1
Name: minimalagent
Version: 0.2.7
Summary: A lightweight agent framework for Amazon Bedrock
Author-email: Niklas Palm <niklas@enpalm.se>
License: MIT
Project-URL: Homepage, https://github.com/nipalm/minimalagent
Project-URL: Repository, https://github.com/nipalm/minimalagent
Classifier: Development Status :: 4 - Beta
Classifier: Intended Audience :: Developers
Classifier: License :: OSI Approved :: MIT License
Classifier: Programming Language :: Python :: 3
Classifier: Programming Language :: Python :: 3.8
Classifier: Programming Language :: Python :: 3.9
Classifier: Programming Language :: Python :: 3.10
Classifier: Programming Language :: Python :: 3.11
Classifier: Programming Language :: Python :: 3.12
Requires-Python: >=3.8
License-File: LICENSE
Requires-Dist: boto3>=1.37.38
Provides-Extra: dev
Requires-Dist: pytest>=6.0.0; extra == "dev"
Requires-Dist: pytest-cov>=4.0.0; extra == "dev"
Requires-Dist: black>=22.0.0; extra == "dev"
Requires-Dist: isort>=5.0.0; extra == "dev"
